setup.py
cromtool/__init__.py
cromtool/main.py
cromtool.egg-info/PKG-INFO
cromtool.egg-info/SOURCES.txt
cromtool.egg-info/dependency_links.txt
cromtool.egg-info/requires.txt
cromtool.egg-info/top_level.txt
scripts/cromtool