Metadata-Version: 1.1
Name: cromtool
Version: 1.3
Summary: Development tool for Cromwell
Home-page: http://github.com/broadinstitute/cromwell
Author: Scott Frazer
Author-email: scott.d.frazer@gmail.com
License: MIT
Platform: UNKNOWN
Classifier: License :: OSI Approved :: MIT License
Classifier: Programming Language :: Python
Classifier: Development Status :: 4 - Beta
Classifier: Intended Audience :: Developers
Classifier: Natural Language :: English
